LICENSE
README.md
pyproject.toml
setup.cfg
setup.py
abantether_python_sdk/__init__.py
abantether_python_sdk/client.py
abantether_python_sdk/client_protocol.py
abantether_python_sdk/config.py
abantether_python_sdk/enums.py
abantether_python_sdk.egg-info/PKG-INFO
abantether_python_sdk.egg-info/SOURCES.txt
abantether_python_sdk.egg-info/dependency_links.txt
abantether_python_sdk.egg-info/requires.txt
abantether_python_sdk.egg-info/top_level.txt
tests/test_client.py
tests/test_portocol.py