Metadata-Version: 2.1
Name: abantether-python-sdk
Version: 0.1.4
Summary: Add your description here
Home-page: https://github.com/Abantether-com/abantether-python-sdk/
Download-URL: https://github.com/imanmousaei/coinexpy/archive/refs/tags/v0.1.4.tar.gz
Author: AbanTether
Author-email: tech@abantether.com
License: MIT
Keywords: abantether,sdk,python,api,exchange,wrapper,trade,crypto,bitcoin
Classifier: Development Status :: 4 - Beta
Classifier: Intended Audience :: Developers
Classifier: Topic :: Software Development :: Build Tools
Classifier: License :: OSI Approved :: MIT License
Classifier: Programming Language :: Python :: 3.8
Classifier: Programming Language :: Python :: 3.9
Classifier: Programming Language :: Python :: 3.10
Classifier: Programming Language :: Python :: 3.11
Classifier: Programming Language :: Python :: 3.12
Classifier: Programming Language :: Python :: 3.13
Requires-Python: >=3.8
License-File: LICENSE
Requires-Dist: flake8>=7.1.1
Requires-Dist: pytest-cov>=6.0.0
Requires-Dist: pytest>=8.3.3
Requires-Dist: requests>=2.32.3
